setup.py
pydistribution/Binomialdistribution.py
pydistribution/Gaussiandistribution.py
pydistribution/Generaldistribution.py
pydistribution/__init__.py
pydistribution.egg-info/PKG-INFO
pydistribution.egg-info/SOURCES.txt
pydistribution.egg-info/dependency_links.txt
pydistribution.egg-info/not-zip-safe
pydistribution.egg-info/top_level.txt