Metadata-Version: 1.0
Name: pydistribution
Version: 1.0
Summary: General ideas about the distributions and their visualizations
Home-page: UNKNOWN
Author: Yalim Demirkesen
Author-email: yalimdemirkesen@gmail.com
License: UNKNOWN
Platform: UNKNOWN
